simple_auth_jwt/__init__.py
simple_auth_jwt/config.py
simple_auth_jwt/core.py
simple_auth_jwt/crypto.py
simple_auth_jwt/db.py
simple_auth_jwt/jwt_handler.py
simple_auth_jwt/middlewares/fastapi.py
simple_auth_jwt/middlewares/flask.py
simple_auth_jwt-0.2.3.dist-info/METADATA
simple_auth_jwt-0.2.3.dist-info/WHEEL
simple_auth_jwt-0.2.3.dist-info/top_level.txt
simple_auth_jwt-0.2.3.dist-info/RECORD
