Metadata-Version: 2.4
Name: simple-auth-jwt
Version: 0.2.3
Summary: Plug-and-play JWT authentication SDK for Flask and FastAPI
Author: Omar Rodrigues
Requires-Python: >=3.9
Requires-Dist: passlib[bcrypt]
Requires-Dist: python-jose
